rithml/__init__.py
rithml/base.py
rithml/classification.py
rithml/clustering.py
rithml/dimred.py
rithml/formatting.py
rithml/regression.py
rithml-1.0.1.dist-info/LICENSE
rithml-1.0.1.dist-info/METADATA
rithml-1.0.1.dist-info/WHEEL
rithml-1.0.1.dist-info/top_level.txt
rithml-1.0.1.dist-info/RECORD
