Metadata-Version: 2.1
Name: rithml
Version: 1.0.1
Summary: Library for common machine learning algorithms
Author-email: Kevin Liu <kevinl9@yahoo.com>
License: GNU GENERAL PUBLIC LICENSE
Project-URL: Homepage, https://github.com/liuxk83/rithml
Project-URL: Bug Tracker, https://github.com/liuxk83/rithml/issues
Classifier: Programming Language :: Python :: 3
Classifier: License :: OSI Approved :: GNU General Public License v3 (GPLv3)
Classifier: Operating System :: OS Independent
Requires-Python: >=3.7
License-File: LICENSE
Requires-Dist: numpy (>=1.20.3)
Requires-Dist: scipy (>=1.7.0)
Requires-Dist: cvxopt (>=1.2.7)
